{
    
	"menu": [
        {
            "name": "生活",
            
			  "submenu": [
                {
                    "name": "家居",
                    
			  				"submenu": [
                        {
                            "name":"照明"
                        },
                        {
                            "name":"家饰"
                        },
                        {
                            "name":"家居收纳"
                        },
                        {
                            "name":"智能家居"
                        },
                        {
                            "name":"计时"
                        },
                        {
                            "name":"工具"
                        },
                        {
                            "name":"清洁"
                        }
                    ]
                },
                {
                    "name": "家具",
                    
			  				"submenu": [
                        {
                            "name":"椅子"
                        },
                        {
                            "name":"桌子"
                        },
                        {
                            "name":"柜子"
                        },
                        {
                            "name":"沙发"
                        },
                        {
                            "name":"床"
                        },
                        {
                            "name":"茶几"
                        }
                    ]
                }
            ]
			  
        },
        
			  {
            "name": "个人佩饰",
            
			  "submenu": [
                {
                    "name": "箱包",
                    
			  				"submenu": [
                        {
                            "name":"单肩包"
                        },
                        {
                            "name":"钱包"
                        },
                        {
                            "name":"双肩包"
                        }
                    ]
                },
                {
                    "name": "手表",
                    
			  				"submenu": [
                        {
                            "name":"智能手表"
                        },
                        {
                            "name":"石英表"
                        },
                        {
                            "name":"机械表"
                        }
                    ]
                }
            ]
			  
        },

        {
            "name": "饮食",
            
			  "submenu": [
                {
                    "name": "厨房用品",
                    
			  				"submenu": [
                        {
                            "name":"照明"
                        },
                        {
                            "name":"家饰"
                        },
                        {
                            "name":"家居收纳"
                        }
                    ]
                },
                {
                    "name": "水具",
                    
			  				"submenu": [
                        {
                            "name":"椅子"
                        },
                        {
                            "name":"桌子"
                        },
                        {
                            "name":"柜子"
                        }
                    ]
                },
                {
                    "name": "厨房电器",
                    
			  				"submenu": [
                        {
                            "name":"椅子"
                        },
                        {
                            "name":"桌子"
                        },
                        {
                            "name":"柜子"
                        }
                    ]
                }
            ]
			  
        }
    ]

}